macrosynergy/__init__.py
macrosynergy/compat.py
macrosynergy/version.py
macrosynergy/download/__init__.py
macrosynergy/download/dataquery.py
macrosynergy/download/dataquery_file_api.py
macrosynergy/download/exceptions.py
macrosynergy/download/external_data_transformer.py
macrosynergy/download/fusion_interface.py
macrosynergy/download/jpm_oauth.py
macrosynergy/download/jpmaqs.py
macrosynergy/download/transaction_costs.py
macrosynergy/learning/__init__.py
macrosynergy/learning/cv_tools.py
macrosynergy/learning/random_effects.py
macrosynergy/learning/forecasting/__init__.py
macrosynergy/learning/forecasting/naive_predictors.py
macrosynergy/learning/forecasting/weighted_regressors.py
macrosynergy/learning/forecasting/bootstrap/__init__.py
macrosynergy/learning/forecasting/bootstrap/base_modified_regressor.py
macrosynergy/learning/forecasting/bootstrap/bootstrap.py
macrosynergy/learning/forecasting/ensemble/__init__.py
macrosynergy/learning/forecasting/ensemble/voting.py
macrosynergy/learning/forecasting/factor_models/__init__.py
macrosynergy/learning/forecasting/factor_models/pls.py
macrosynergy/learning/forecasting/linear_model/__init__.py
macrosynergy/learning/forecasting/linear_model/global_local.py
macrosynergy/learning/forecasting/linear_model/sur.py
macrosynergy/learning/forecasting/linear_model/lad_regressors/__init__.py
macrosynergy/learning/forecasting/linear_model/lad_regressors/lad_regressor.py
macrosynergy/learning/forecasting/linear_model/lad_regressors/weighted_lad_regressors.py
macrosynergy/learning/forecasting/linear_model/ls_regressors/__init__.py
macrosynergy/learning/forecasting/linear_model/ls_regressors/modified_ls_regressors.py
macrosynergy/learning/forecasting/linear_model/ls_regressors/weighted_ls_regressors.py
macrosynergy/learning/forecasting/meta_estimators/__init__.py
macrosynergy/learning/forecasting/meta_estimators/country_by_country_regressions.py
macrosynergy/learning/forecasting/meta_estimators/dataframe_transformer.py
macrosynergy-1.5.1.dist-info/licenses/LICENSE
macrosynergy-1.5.1.dist-info/METADATA
macrosynergy-1.5.1.dist-info/WHEEL
macrosynergy-1.5.1.dist-info/top_level.txt
macrosynergy-1.5.1.dist-info/RECORD
