Metadata-Version: 2.4
Name: macrosynergy
Version: 1.5.1
Summary: Macrosynergy Quant Research Package
Author-email: Macrosynergy <info@macrosynergy.com>
License: BSD 3-Clause License
Project-URL: homepage, https://www.macrosynergy.com
Project-URL: repository, https://github.com/macrosynergy/macrosynergy/
Project-URL: documentation, https://docs.macrosynergy.com
Project-URL: tracker, https://github.com/macrosynergy/macrosynergy/issues
Platform: Windows
Platform: Linux
Platform: Mac OS-X
Classifier: Development Status :: 4 - Beta
Classifier: Environment :: Console
Classifier: Intended Audience :: Science/Research
Classifier: Intended Audience :: Financial and Insurance Industry
Classifier: Intended Audience :: Developers
Classifier: License :: OSI Approved :: BSD License
Classifier: Programming Language :: Python
Classifier: Programming Language :: Python :: 3
Classifier: Programming Language :: Python :: 3 :: Only
Classifier: Programming Language :: Python :: 3.8
Classifier: Programming Language :: Python :: 3.9
Classifier: Programming Language :: Python :: 3.10
Classifier: Programming Language :: Python :: 3.11
Classifier: Programming Language :: Python :: 3.12
Classifier: Topic :: Software Development
Classifier: Topic :: Scientific/Engineering
Classifier: Typing :: Typed
Classifier: Operating System :: OS Independent
Requires-Python: >=3.7
License-File: LICENSE
Requires-Dist: seaborn>=0.13.0
Requires-Dist: matplotlib>=3.6.0
Requires-Dist: pandas<3.0.0,>=1.3.5
Requires-Dist: statsmodels>=0.13.2
Requires-Dist: scikit-learn>=1.2.2
Requires-Dist: numpy>=1.21.6
Requires-Dist: requests>=2.27.1
Requires-Dist: tqdm>=4.62
Requires-Dist: Jinja2>=2.10
Requires-Dist: joblib>=1.3.0
Requires-Dist: pyarrow>=11.0.0
Requires-Dist: scipy<=1.15.3
Requires-Dist: polars>=1.0.0
Requires-Dist: torch>=1.11.0
Provides-Extra: test
Requires-Dist: pytest<9.0.0,>=7.0.0; extra == "test"
Requires-Dist: pytest-cov>3.0.0; extra == "test"
Requires-Dist: coverage>=6.0.0; extra == "test"
Requires-Dist: pytest-xdist>=3.3.1; extra == "test"
Requires-Dist: flake8>=4.0.1; extra == "test"
Requires-Dist: parameterized>=0.9.0; extra == "test"
Requires-Dist: linearmodels>=4.28; extra == "test"
Provides-Extra: excel
Requires-Dist: openpyxl>=3.0.10; extra == "excel"
Provides-Extra: notebook
Requires-Dist: notebook>=6.0.0; extra == "notebook"
Requires-Dist: ipywidgets>=7.6.5; extra == "notebook"
Requires-Dist: ipython>=7.28.0; extra == "notebook"
Requires-Dist: jupyter>=1.0.0; extra == "notebook"
Requires-Dist: ipykernel>=6.4.1; extra == "notebook"
Provides-Extra: format
Requires-Dist: black>=22.1.0; extra == "format"
Provides-Extra: docs
Requires-Dist: pydata-sphinx-theme==0.14.4; extra == "docs"
Requires-Dist: Sphinx==7.1.2; extra == "docs"
Requires-Dist: sphinx-autodoc-typehints==1.19.1; extra == "docs"
Requires-Dist: sphinx-automodapi==0.16.0; extra == "docs"
Requires-Dist: sphinx-remove-toctrees==0.0.3; extra == "docs"
Requires-Dist: sphinx_design==0.5.0; extra == "docs"
Requires-Dist: myst_parser==2.0.0; extra == "docs"
Requires-Dist: sphinx-copybutton==0.5.0; extra == "docs"
Requires-Dist: sphinxcontrib-mermaid>=0.8.0; extra == "docs"
Requires-Dist: requests>=2.32.2; extra == "docs"
Requires-Dist: packaging>=21.0; extra == "docs"
Requires-Dist: zipp>=3.19.1; extra == "docs"
Provides-Extra: all
Requires-Dist: openpyxl>=3.0.10; extra == "all"
Requires-Dist: notebook>=6.0.0; extra == "all"
Requires-Dist: ipywidgets>=7.6.5; extra == "all"
Requires-Dist: ipython>=7.28.0; extra == "all"
Requires-Dist: jupyter>=1.0.0; extra == "all"
Requires-Dist: ipykernel>=6.4.1; extra == "all"
Requires-Dist: black>=22.1.0; extra == "all"
Requires-Dist: pytest<9.0.0,>=7.0.0; extra == "all"
Requires-Dist: pytest-cov>3.0.0; extra == "all"
Requires-Dist: coverage>=6.0.0; extra == "all"
Requires-Dist: pytest-xdist>=3.3.1; extra == "all"
Requires-Dist: flake8>=4.0.1; extra == "all"
Requires-Dist: parameterized>=0.9.0; extra == "all"
Requires-Dist: pydata-sphinx-theme==0.14.4; extra == "all"
Requires-Dist: Sphinx==7.1.2; extra == "all"
Requires-Dist: sphinx-autodoc-typehints==1.19.1; extra == "all"
Requires-Dist: sphinx-automodapi==0.16.0; extra == "all"
Requires-Dist: sphinx-remove-toctrees==0.0.3; extra == "all"
Requires-Dist: sphinx_design==0.5.0; extra == "all"
Requires-Dist: myst_parser==2.0.0; extra == "all"
Requires-Dist: sphinx-copybutton==0.5.0; extra == "all"
Requires-Dist: requests>=2.32.2; extra == "all"
Requires-Dist: packaging>=21.0; extra == "all"
Requires-Dist: zipp>=3.19.1; extra == "all"
Dynamic: license-file
